LICENSE
MANIFEST.in
README.md
setup.py
daterangefilter/__init__.py
daterangefilter/apps.py
daterangefilter/filters.py
daterangefilter/models.py
daterangefilter/tests.py
daterangefilter/locale/ru/LC_MESSAGES/django.mo
daterangefilter/locale/ru/LC_MESSAGES/django.po
daterangefilter/static/daterangefilter/daterangepicker/daterangepicker.css
daterangefilter/static/daterangefilter/daterangepicker/daterangepicker.min.js
daterangefilter/static/daterangefilter/moment/moment-with-locales.min.js
daterangefilter/static/daterangefilter/moment/moment.min.js
daterangefilter/static/daterangefilter/moment/locale/ru.js
daterangefilter/templates/daterangefilter/_future_ranges.html
daterangefilter/templates/daterangefilter/_load_momentjs.html
daterangefilter/templates/daterangefilter/_past_ranges.html
daterangefilter/templates/daterangefilter/daterangefilter.html
daterangefilter/templates/daterangefilter/ranges.html
daterangefilter/templates/daterangefilter/suit_daterangefilter.html
django_daterangefilter_plus.egg-info/PKG-INFO
django_daterangefilter_plus.egg-info/SOURCES.txt
django_daterangefilter_plus.egg-info/dependency_links.txt
django_daterangefilter_plus.egg-info/not-zip-safe
django_daterangefilter_plus.egg-info/top_level.txt